LICENSE
MANIFEST.in
README.rst
setup.py
mezzanine_wymeditor/__init__.py
mezzanine_wymeditor/defaults.py
mezzanine_wymeditor/models.py
mezzanine_wymeditor/widgets.py
mezzanine_wymeditor.egg-info/PKG-INFO
mezzanine_wymeditor.egg-info/SOURCES.txt
mezzanine_wymeditor.egg-info/dependency_links.txt
mezzanine_wymeditor.egg-info/not-zip-safe
mezzanine_wymeditor.egg-info/top_level.txt
mezzanine_wymeditor/static/mezzanine_wymeditor/css/wym.css
mezzanine_wymeditor/static/mezzanine_wymeditor/img/filebrowser_icon_show.png
mezzanine_wymeditor/static/mezzanine_wymeditor/js/setup.js
mezzanine_wymeditor/static/mezzanine_wymeditor/wymeditor/jquery.wymeditor.js
mezzanine_wymeditor/static/mezzanine_wymeditor/wymeditor/jquery.wymeditor.min.js
mezzanine_wymeditor/static/mezzanine_wymeditor/wymeditor/iframe/default/lbl-article.png
mezzanine_wymeditor/static/mezzanine_wymeditor/wymeditor/iframe/default/lbl-aside.png
mezzanine_wymeditor/static/mezzanine_wymeditor/wymeditor/iframe/default/lbl-blockquote.png
mezzanine_wymeditor/static/mezzanine_wymeditor/wymeditor/iframe/default/lbl-command.png
mezzanine_wymeditor/static/mezzanine_wymeditor/wymeditor/iframe/default/lbl-details.png
mezzanine_wymeditor/static/mezzanine_wymeditor/wymeditor/iframe/default/lbl-div.png
mezzanine_wymeditor/static/mezzanine_wymeditor/wymeditor/iframe/default/lbl-figcaption.png
mezzanine_wymeditor/static/mezzanine_wymeditor/wymeditor/iframe/default/lbl-figure.png
mezzanine_wymeditor/static/mezzanine_wymeditor/wymeditor/iframe/default/lbl-footer.png
mezzanine_wymeditor/static/mezzanine_wymeditor/wymeditor/iframe/default/lbl-h1.png
mezzanine_wymeditor/static/mezzanine_wymeditor/wymeditor/iframe/default/lbl-h2.png
mezzanine_wymeditor/static/mezzanine_wymeditor/wymeditor/iframe/default/lbl-h3.png
mezzanine_wymeditor/static/mezzanine_wymeditor/wymeditor/iframe/default/lbl-h4.png
mezzanine_wymeditor/static/mezzanine_wymeditor/wymeditor/iframe/default/lbl-h5.png
mezzanine_wymeditor/static/mezzanine_wymeditor/wymeditor/iframe/default/lbl-h6.png
mezzanine_wymeditor/static/mezzanine_wymeditor/wymeditor/iframe/default/lbl-header.png
mezzanine_wymeditor/static/mezzanine_wymeditor/wymeditor/iframe/default/lbl-hgroup.png
