Metadata-Version: 1.1
Name: mezzanine-wymeditor
Version: 0.3
Summary: WYMeditor RichText widget for Mezzanine
Home-page: https://github.com/excieve/mezzanine-wymeditor
Author: Artem Hluvchynskyi
Author-email: excieve@gmail.com
License: BSD
Keywords: mezzanine wymeditor
Platform: UNKNOWN
Classifier: Development Status :: 4 - Beta
Classifier: Intended Audience :: Developers
Classifier: Topic :: Text Editors
Classifier: Topic :: Text Processing :: Markup :: HTML
Classifier: Topic :: Software Development :: Libraries :: Python Modules
Classifier: License :: OSI Approved :: BSD License
Classifier: Operating System :: OS Independent
Classifier: Programming Language :: Python
Classifier: Programming Language :: Python :: 2
Classifier: Programming Language :: JavaScript
Classifier: Framework :: Django
Classifier: Environment :: Web Environment
